[{"headers": [["Consolidated Statements of Cash Flows - USD ($) $ in Thousands", "3 Months Ended", "9 Months Ended"], ["Sep. 30, 2022", "Sep. 30, 2021", "Sep. 30, 2022", "Sep. 30, 2021"]], "sections": ["Cash flows from operating activities", "Adjustments to reconcile net loss to net cash provided by (used in) operating activities:", "Change in operating assets and liabilities, net of effect of acquisitions:", "Cash flows from investing activities", "Cash flows from financing activities", "Supplemental disclosures"], "data": [["Net loss", "$ (359,502)", "$ (71,959)", "$ (1,141,193)", "$ (510,505)"], ["Depreciation and amortization", "36,291", "32,510", "153,682", "84,278"], ["Stock-based compensation", "342,959", "300,898", "937,213", "794,571"], ["Amortization of debt issuance costs", "1,835", "1,109", "5,028", "3,301"], ["Losses (gains) on debt and equity securities, net", "(75,778)", "(121,007)", "15,559", "(223,527)"], ["Induced conversion expense related to convertible notes", "", "4,536", "", "41,538"], ["Other", "12,133", "(732)", "16,337", "4,019"], ["Accounts receivable, net of allowance", "17,410", "(132,908)", "62,436", "(178,044)"], ["Prepaid expenses and other current assets", "7,044", "(4,191)", "(32,114)", "(15,562)"], ["Operating lease right-of-use assets", "17,922", "11,470", "53,205", "35,217"], ["Other assets", "(5,095)", "(4,204)", "(12,633)", "(5,440)"], ["Accounts payable", "9,381", "11,084", "60,442", "17,430"], ["Accrued expenses and other current liabilities", "60,036", "56,687", "(17,184)", "89,726"], ["Operating lease liabilities", "(12,116)", "(13,911)", "(46,431)", "(35,265)"], ["Other liabilities", "3,425", "2,170", "4,976", "5,615"], ["Net cash provided by (used in) operating activities", "55,945", "71,552", "59,323", "107,352"], ["Purchases of property and equipment", "(37,836)", "(19,836)", "(82,381)", "(45,310)"], ["Purchases of strategic investments", "(6,000)", "(735)", "(12,350)", "(33,510)"], ["Sales of strategic investments", "", "", "63,276", "36,435"], ["Cash paid for acquisitions, net of cash acquired", "(19,650)", "(37,375)", "(31,658)", "(176,591)"], ["Purchases of marketable securities", "(821,830)", "(609,176)", "(2,732,266)", "(1,896,766)"], ["Sales of marketable securities", "39,158", "19,999", "51,917", "367,555"], ["Maturities of marketable securities", "923,871", "492,921", "1,820,442", "2,006,744"], ["Other", "(12,648)", "(1,000)", "(18,141)", "(1,335)"], ["Net cash provided by (used in) investing activities", "65,065", "(155,202)", "(941,161)", "257,222"], ["Proceeds from issuance of convertible notes, net of issuance costs", "", "", "1,483,500", "1,137,227"], ["Purchase of capped calls", "", "", "(177,000)", "(86,825)"], ["Proceeds from the exercise of stock options", "217", "4,045", "3,871", "11,755"], ["Payments of debt issuance costs", "", "", "(3,006)", ""], ["Repurchases of Class A non-voting common stock", "(500,513)", "", "(500,513)", ""], ["Net cash provided by (used in) financing activities", "(500,296)", "4,045", "806,852", "1,062,157"], ["Change in cash, cash equivalents, and restricted cash", "(379,286)", "(79,605)", "(74,986)", "1,426,731"], ["Cash, cash equivalents, and restricted cash, beginning of period", "2,299,023", "2,052,879", "1,994,723", "546,543"], ["Cash, cash equivalents, and restricted cash, end of period", "1,919,737", "1,973,274", "1,919,737", "1,973,274"], ["Cash paid for income taxes, net", "1,482", "1,940", "8,966", "16,228"], ["Cash paid for interest", "$ 4,186", "$ 3,508", "$ 8,191", "$ 10,249"]]}, {"headers": [["Consolidated Statements of Operations - USD ($) shares in Thousands, $ in Thousands", "3 Months Ended", "9 Months Ended"], ["Sep. 30, 2022", "Sep. 30, 2021", "Sep. 30, 2022", "Sep. 30, 2021"]], "sections": ["Income Statement [Abstract]", "Costs and expenses:", "Net loss per share attributable to Class A, Class B, and Class C common stockholders (Note 3):", "Weighted average shares used in computation of net loss per share:"], "data": [["Revenue", "$ 1,128,476", "$ 1,067,471", "$ 3,302,112", "$ 2,819,163"], ["Cost of revenue", "466,757", "443,473", "1,334,031", "1,301,095"], ["Research and development", "564,258", "412,021", "1,524,858", "1,131,272"], ["Sales and marketing", "270,336", "217,526", "823,596", "547,536"], ["General and administrative", "262,367", "175,275", "727,336", "516,202"], ["Total costs and expenses", "1,563,718", "1,248,295", "4,409,821", "3,496,105"], ["Operating loss", "(435,242)", "(180,824)", "(1,107,709)", "(676,942)"], ["Interest income", "18,445", "1,257", "29,899", "3,645"], ["Interest expense", "(5,425)", "(4,031)", "(16,147)", "(13,626)"], ["Other income (expense), net", "71,961", "112,631", "(22,486)", "176,971"], ["Loss before income taxes", "(350,261)", "(70,967)", "(1,116,443)", "(509,952)"], ["Income tax benefit (expense)", "(9,241)", "(992)", "(24,750)", "(553)"], ["Net loss", "$ (359,502)", "$ (71,959)", "$ (1,141,193)", "$ (510,505)"], ["Basic", "$ (0.22)", "$ (0.05)", "$ (0.70)", "$ (0.33)"], ["Diluted", "$ (0.22)", "$ (0.05)", "$ (0.70)", "$ (0.33)"], ["Basic", "1,608,523", "1,580,966", "1,619,885", "1,543,568"], ["Diluted", "1,608,523", "1,580,966", "1,619,885", "1,543,568"]]}, {"headers": [["Consolidated Balance Sheets - USD ($) $ in Thousands", "Sep. 30, 2022", "Dec. 31, 2021"]], "sections": ["Current assets", "Current liabilities", "Stockholders\u2019 equity", "Stockholders\u2019 equity", "Stockholders\u2019 equity"], "data": [["Cash and cash equivalents", "$ 1,918,845", "$ 1,993,809"], ["Marketable securities", "2,510,107", "1,699,076"], ["Accounts receivable, net of allowance", "992,747", "1,068,873"], ["Prepaid expenses and other current assets", "115,973", "92,244"], ["Total current assets", "5,537,672", "4,854,002"], ["Property and equipment, net", "240,752", "202,644"], ["Operating lease right-of-use assets", "383,037", "322,252"], ["Intangible assets, net", "229,128", "277,654"], ["Goodwill", "1,632,796", "1,588,452"], ["Other assets", "261,809", "291,302"], ["Total assets", "8,285,194", "7,536,306"], ["Accounts payable", "188,605", "125,282"], ["Operating lease liabilities", "57,913", "52,396"], ["Accrued expenses and other current liabilities", "893,414", "674,108"], ["Total current liabilities", "1,139,932", "851,786"], ["Convertible senior notes, net", "3,740,804", "2,253,087"], ["Operating lease liabilities, noncurrent", "384,495", "325,509"], ["Other liabilities", "119,701", "315,756"], ["Total liabilities", "5,384,932", "3,746,138"], ["Commitments and contingencies (Note 8)", "", ""], ["Additional paid-in capital", "12,859,689", "12,069,097"], ["Accumulated deficit", "(9,425,659)", "(8,284,466)"], ["Accumulated other comprehensive income (loss)", "(33,271)", "5,521"], ["Total stockholders\u2019 equity", "2,900,262", "3,790,168"], ["Total liabilities and stockholders\u2019 equity", "8,285,194", "7,536,306"], ["Class A Non-voting Common Stock", "", ""], ["Common stock, value", "14", "14"], ["Treasury stock, value", "(500,513)", ""], ["Class C Voting Common Stock", "", ""], ["Common stock, value", "$ 2", "$ 2"]]}, {"headers": [["Consolidated Statements of Stockholders' Equity - USD ($) shares in Thousands, $ in Thousands", "Total", "Additional Paid-in Capital", "Additional Paid-in Capital \nCumulative Effect, Period of Adoption, Adjustment", "Accumulated Deficit", "Accumulated Deficit \nCumulative Effect, Period of Adoption, Adjustment", "Accumulated Other Comprehensive Income (Loss)", "Class A Common Stock", "Class A Common Stock \nCommon Stock", "Class A Common Stock \nTreasury stock", "Class B Voting Common Stock", "Class B Voting Common Stock \nCommon Stock", "Class C Voting Common Stock", "Class C Voting Common Stock \nCommon Stock"]], "sections": [], "data": [["Balance, beginning of period, shares at Dec. 31, 2020", "", "", "", "", "", "", "", "1,248,010", "", "", "23,696", "", "231,627"], ["Balance, beginning of period at Dec. 31, 2020", "", "$ 10,200,141", "$ (664,021)", "$ (7,891,542)", "$ 95,031", "$ 21,363", "", "$ 12", "", "", "", "", "$ 2"], ["Stock-based compensation expense", "", "792,454", "", "", "", "", "", "", "", "", "", "", ""], ["Shares issued in connection with exercise of stock options under stock-based compensation plans, shares", "", "", "", "", "", "", "", "890", "", "", "67", "", ""], ["Shares issued in connection with exercise of stock options under stock-based compensation plans", "", "11,755", "", "", "", "", "", "", "", "", "", "", ""], ["Issuance of non-voting common stock in connection with acquisitions , shares", "", "", "", "", "", "", "", "5,817", "", "", "", "", ""], ["Issuance of Class A non-voting common stock in connection with acquisitions", "", "308,636", "", "", "", "", "", "", "", "", "", "", ""], ["Issuance of voting/non-voting common stock for vesting of restricted stock units and restricted stock awards, net, shares", "", "", "", "", "", "", "", "42,636", "", "", "", "", ""], ["Issuance of Class A non-voting common stock for the induced conversion related to convertible senior notes", "", "1,175,198", "", "", "", "", "", "", "", "", "", "", ""], ["Issuance of Class A non-voting common stock for the induced conversion related to convertible senior notes, shares", "", "", "", "", "", "", "", "52,410", "", "", "", "", ""], ["Conversion of stock to voting/non-voting common stock, shares", "", "", "", "", "", "", "", "127", "", "", "(127)", "", ""], ["Conversion of stock to voting/non-voting common stock", "", "", "", "", "", "", "", "$ 1", "", "", "", "", ""], ["Purchase of capped calls", "", "(86,825)", "", "", "", "", "", "", "", "", "", "", ""], ["Net loss", "$ (510,505)", "", "", "(510,505)", "", "", "$ (426,077)", "", "", "$ (7,822)", "", "$ (76,606)", ""], ["Other comprehensive income (loss), net of tax", "$ (11,584)", "", "", "", "", "(11,584)", "", "", "", "", "", "", ""], ["Balance, end of period, shares at Sep. 30, 2021", "1,605,153", "", "", "", "", "", "", "1,349,890", "", "", "23,636", "", "231,627"], ["Balance, end of period at Sep. 30, 2021", "$ 3,440,116", "11,737,338", "", "(8,307,016)", "", "9,779", "", "$ 13", "", "", "", "", "$ 2"], ["Balance, beginning of period, shares at Dec. 31, 2020", "", "", "", "", "", "", "", "1,248,010", "", "", "23,696", "", "231,627"], ["Balance, beginning of period at Dec. 31, 2020", "", "10,200,141", "$ (664,021)", "(7,891,542)", "$ 95,031", "21,363", "", "$ 12", "", "", "", "", "$ 2"], ["Balance, end of period, shares at Dec. 31, 2021", "", "", "", "", "", "", "", "1,364,887", "", "", "22,769", "", "231,627"], ["Balance, end of period at Dec. 31, 2021", "3,790,168", "12,069,097", "", "(8,284,466)", "", "5,521", "", "$ 14", "", "", "", "", "$ 2"], ["Balance, beginning of period, shares at Jun. 30, 2021", "", "", "", "", "", "", "", "1,321,477", "", "", "23,640", "", "231,627"], ["Balance, beginning of period at Jun. 30, 2021", "", "11,129,196", "", "(8,235,057)", "", "13,847", "", "$ 13", "", "", "", "", "$ 2"], ["Stock-based compensation expense", "", "299,450", "", "", "", "", "", "", "", "", "", "", ""], ["Shares issued in connection with exercise of stock options under stock-based compensation plans, shares", "", "", "", "", "", "", "", "342", "", "", "59", "", ""], ["Shares issued in connection with exercise of stock options under stock-based compensation plans", "", "4,045", "", "", "", "", "", "", "", "", "", "", ""], ["Issuance of non-voting common stock in connection with acquisitions , shares", "", "", "", "", "", "", "", "84", "", "", "", "", ""], ["Issuance of voting/non-voting common stock for vesting of restricted stock units and restricted stock awards, net, shares", "", "", "", "", "", "", "", "13,912", "", "", "", "", ""], ["Issuance of Class A non-voting common stock for the induced conversion related to convertible senior notes", "", "304,647", "", "", "", "", "", "", "", "", "", "", ""], ["Issuance of Class A non-voting common stock for the induced conversion related to convertible senior notes, shares", "", "", "", "", "", "", "", "14,012", "", "", "", "", ""], ["Conversion of stock to voting/non-voting common stock, shares", "", "", "", "", "", "", "", "63", "", "", "(63)", "", ""], ["Net loss", "(71,959)", "", "", "(71,959)", "", "", "(60,340)", "", "", "(1,076)", "", "(10,543)", ""], ["Other comprehensive income (loss), net of tax", "$ (4,068)", "", "", "", "", "(4,068)", "", "", "", "", "", "", ""], ["Balance, end of period, shares at Sep. 30, 2021", "1,605,153", "", "", "", "", "", "", "1,349,890", "", "", "23,636", "", "231,627"], ["Balance, end of period at Sep. 30, 2021", "$ 3,440,116", "11,737,338", "", "(8,307,016)", "", "9,779", "", "$ 13", "", "", "", "", "$ 2"], ["Balance, beginning of period, shares at Dec. 31, 2021", "", "", "", "", "", "", "", "1,364,887", "", "", "22,769", "", "231,627"], ["Balance, beginning of period at Dec. 31, 2021", "3,790,168", "12,069,097", "", "(8,284,466)", "", "5,521", "", "$ 14", "", "", "", "", "$ 2"], ["Stock-based compensation expense", "", "919,669", "", "", "", "", "", "", "", "", "", "", ""], ["Shares issued in connection with exercise of stock options under stock-based compensation plans, shares", "", "", "", "", "", "", "", "286", "", "", "10", "", ""], ["Shares issued in connection with exercise of stock options under stock-based compensation plans", "", "3,884", "", "", "", "", "", "", "", "", "", "", ""], ["Issuance of non-voting common stock in connection with acquisitions , shares", "", "", "", "", "", "", "", "1,277", "", "", "", "", ""], ["Issuance of Class A non-voting common stock in connection with acquisitions", "", "44,039", "", "", "", "", "", "", "", "", "", "", ""], ["Issuance of voting/non-voting common stock for vesting of restricted stock units and restricted stock awards, net, shares", "", "", "", "", "", "", "", "36,325", "", "", "", "", ""], ["Conversion of stock to voting/non-voting common stock, shares", "", "", "", "", "", "", "", "141", "", "", "(141)", "", ""], ["Repurchases of Class A non-voting common stock, shares", "", "", "", "", "", "", "", "(51,312)", "51,312", "", "", "", ""], ["Repurchases of Class A non-voting common stock", "", "", "", "", "", "", "", "", "$ (500,513)", "", "", "", ""], ["Purchase of capped calls", "", "(177,000)", "", "", "", "", "", "", "", "", "", "", ""], ["Net loss", "(1,141,193)", "", "", "(1,141,193)", "", "", "$ (962,047)", "", "", "(15,967)", "", "(163,179)", ""], ["Other comprehensive income (loss), net of tax", "$ (38,792)", "", "", "", "", "(38,792)", "", "", "", "", "", "", ""], ["Balance, end of period, shares at Sep. 30, 2022", "1,657,181", "", "", "", "", "", "", "1,351,604", "51,312", "", "22,638", "", "231,627"], ["Balance, end of period at Sep. 30, 2022", "$ 2,900,262", "12,859,689", "", "(9,425,659)", "", "(33,271)", "", "$ 14", "$ (500,513)", "", "", "", "$ 2"], ["Balance, beginning of period, shares at Jun. 30, 2022", "", "", "", "", "", "", "", "1,390,709", "", "", "22,638", "", "231,627"], ["Balance, beginning of period at Jun. 30, 2022", "", "12,529,743", "", "(9,066,157)", "", "(19,843)", "", "$ 14", "", "", "", "", "$ 2"], ["Stock-based compensation expense", "", "329,728", "", "", "", "", "", "", "", "", "", "", ""], ["Shares issued in connection with exercise of stock options under stock-based compensation plans, shares", "", "", "", "", "", "", "", "26", "", "", "", "", ""], ["Shares issued in connection with exercise of stock options under stock-based compensation plans", "", "218", "", "", "", "", "", "", "", "", "", "", ""], ["Issuance of voting/non-voting common stock for vesting of restricted stock units and restricted stock awards, net, shares", "", "", "", "", "", "", "", "12,181", "", "", "", "", ""], ["Repurchases of Class A non-voting common stock, shares", "", "", "", "", "", "", "(51,300)", "(51,312)", "51,312", "", "", "", ""], ["Repurchases of Class A non-voting common stock", "", "", "", "", "", "", "$ (500,500)", "", "$ (500,513)", "", "", "", ""], ["Net loss", "(359,502)", "", "", "(359,502)", "", "", "$ (302,674)", "", "", "$ (5,060)", "", "$ (51,768)", ""], ["Other comprehensive income (loss), net of tax", "$ (13,428)", "", "", "", "", "(13,428)", "", "", "", "", "", "", ""], ["Balance, end of period, shares at Sep. 30, 2022", "1,657,181", "", "", "", "", "", "", "1,351,604", "51,312", "", "22,638", "", "231,627"], ["Balance, end of period at Sep. 30, 2022", "$ 2,900,262", "$ 12,859,689", "", "$ (9,425,659)", "", "$ (33,271)", "", "$ 14", "$ (500,513)", "", "", "", "$ 2"]]}]