[{"headers": [["CONSOLIDATED STATEMENTS OF INCOME - USD ($) shares in Millions, $ in Millions", "12 Months Ended"], ["Jan. 28, 2018", "Jan. 29, 2017", "Jan. 31, 2016"]], "sections": ["Operating expenses"], "data": [["Revenue", "", "$ 9,714", "$ 6,910", "$ 5,010"], ["Cost of revenue", "", "3,892", "2,847", "2,199"], ["Gross profit", "", "5,822", "4,063", "2,811"], ["Research and development", "", "1,797", "1,463", "1,331"], ["Sales, general and administrative", "", "815", "663", "602"], ["Restructuring and other charges", "", "0", "3", "131"], ["Total operating expenses", "", "2,612", "2,129", "2,064"], ["Income from operations", "", "3,210", "1,934", "747"], ["Interest income", "", "69", "54", "39"], ["Interest expense", "", "(61)", "(58)", "(47)"], ["Other, net", "", "(22)", "(25)", "4"], ["Total other income (expense)", "", "(14)", "(29)", "(4)"], ["Income before income tax", "", "3,196", "1,905", "743"], ["Income tax expense", "", "149", "239", "129"], ["Net income", "", "$ 3,047", "$ 1,666", "$ 614"], ["Basic net income per share", "[1]", "$ 5.09", "$ 3.08", "$ 1.13"], ["Diluted net income per share", "[2]", "$ 4.82", "$ 2.57", "$ 1.08"], ["Weighted average shares used in basic per share computation", "", "599", "541", "543"], ["Weighted average shares used in diluted per share computation", "", "632", "649", "569"], ["Cash dividends declared and paid per common share", "", "$ 0.570", "$ 0.485", "$ 0.395"], [""], ["[1]\nCalculated as net income divided by basic weighted average shares.\n\n\n[2]\nCalculated as net income divided by diluted weighted average shares.", "[1]", "Calculated as net income divided by basic weighted average shares.", "[2]", "Calculated as net income divided by diluted weighted average shares."], ["[1]", "Calculated as net income divided by basic weighted average shares."], ["[2]", "Calculated as net income divided by diluted weighted average shares."]]}, {"headers": [["CONSOLIDATED BALANCE SHEETS - USD ($) $ in Millions", "Jan. 28, 2018", "Jan. 29, 2017"]], "sections": ["Current assets:", "Current liabilities:", "Shareholders' equity"], "data": [["Cash and cash equivalents", "$ 4,002", "$ 1,766"], ["Marketable securities", "3,106", "5,032"], ["Accounts receivable, net", "1,265", "826"], ["Inventories", "796", "794"], ["Prepaid expenses and other current assets", "86", "118"], ["Total current assets", "9,255", "8,536"], ["Property and equipment, net", "997", "521"], ["Goodwill", "618", "618"], ["Intangible assets, net", "52", "104"], ["Other assets", "319", "62"], ["Total assets", "11,241", "9,841"], ["Accounts payable", "596", "485"], ["Accrued and other current liabilities", "542", "507"], ["Convertible short-term debt", "15", "796"], ["Total current liabilities", "1,153", "1,788"], ["Long-term debt", "1,985", "1,983"], ["Other long-term liabilities", "632", "277"], ["Total Liabilities", "3,770", "4,048"], ["Commitments and contingencies - see Note 12", "", ""], ["Convertible debt conversion obligation", "0", "31"], ["Preferred stock", "0", "0"], ["Common stock", "1", "1"], ["Additional paid-in capital", "5,351", "4,708"], ["Treasury stock, at cost", "(6,650)", "(5,039)"], ["Accumulated other comprehensive loss", "(18)", "(16)"], ["Retained earnings", "8,787", "6,108"], ["Total shareholders' equity", "7,471", "5,762"], ["Total liabilities, convertible debt conversion obligation and shareholders' equity", "$ 11,241", "$ 9,841"]]}, {"headers": [["CONSOLIDATED STATEMENTS OF SHAREHOLDERS' EQUITY - USD ($) shares in Millions, $ in Millions", "Total", "Common Stock Outstanding", "Additional Paid-in Capital", "Treasury Stock", "Accumulated Other Comprehensive Income (Loss)", "Retained Earnings"]], "sections": ["Increase (Decrease) in Shareholders' Equity", "Increase (Decrease) in Shareholders' Equity", "Increase (Decrease) in Shareholders' Equity"], "data": [["Beginning common stock, shares, outstanding at Jan. 25, 2015", "", "545", "", "", "", ""], ["Beginning Balances, shareholders' equity at Jan. 25, 2015", "$ 4,418", "$ 1", "$ 3,855", "$ (3,395)", "$ 8", "$ 3,949"], ["Other comprehensive income (loss)", "(12)", "", "", "", "(12)", ""], ["Net income", "614", "", "", "", "", "614"], ["Issuance of common stock from stock plans, shares", "", "22", "", "", "", ""], ["Issuance of common stock from stock plans, value", "186", "", "186", "", "", ""], ["Tax withholding related to vesting of restricted stock units, shares", "", "(3)", "", "", "", ""], ["Tax withholding related to vesting of restricted stock units, value", "(66)", "", "", "(66)", "", ""], ["Tax benefit from stock-based compensation", "10", "", "10", "", "", ""], ["Share repurchase, shares", "", "(25)", "", "", "", ""], ["Share repurchase, value", "(587)", "", "", "(587)", "", ""], ["Cash dividends declared and paid", "$ (213)", "", "", "", "", "(213)"], ["Cash dividends declared and paid per common share", "$ 0.395", "", "", "", "", ""], ["Stock-based compensation", "$ 206", "", "206", "", "", ""], ["Reclassification of convertible debt conversion obligation", "(87)", "", "(87)", "", "", ""], ["Ending common stock, shares, outstanding at Jan. 31, 2016", "", "539", "", "", "", ""], ["Ending Balances, shareholders' equity at Jan. 31, 2016", "4,469", "$ 1", "4,170", "(4,048)", "(4)", "4,350"], ["Retained earnings adjustment due to adoption of an accounting standard related to stock-based compensation", "353", "", "", "", "", "353"], ["Other comprehensive income (loss)", "(12)", "", "", "", "(12)", ""], ["Net income", "1,666", "", "", "", "", "1,666"], ["Issuance of common stock in exchange for warrants, shares", "", "44", "", "", "", ""], ["Issuance of common stock in exchange for warrants, value", "(1)", "", "(1)", "", "", ""], ["Issuance of common stock from stock plans, shares", "", "20", "", "", "", ""], ["Issuance of common stock from stock plans, value", "167", "", "167", "", "", ""], ["Convertible debt conversion, shares", "", "23", "", "", "", ""], ["Convertible debt conversion, value", "(6)", "", "(6)", "", "", ""], ["Tax withholding related to vesting of restricted stock units, shares", "", "(3)", "", "", "", ""], ["Tax withholding related to vesting of restricted stock units, value", "(177)", "", "", "(177)", "", ""], ["Share repurchase, shares", "", "(15)", "", "", "", ""], ["Share repurchase, value", "(739)", "", "", "(739)", "", ""], ["Exercise of convertible note hedges, shares", "", "23", "", "", "", ""], ["Exercise of convertible note hedges - APIC, value", "", "", "75", "", "", ""], ["Exercise of convertible note hedges - treasury stock, value", "", "", "", "(75)", "", ""], ["Cash dividends declared and paid", "$ (261)", "", "", "", "", "(261)"], ["Cash dividends declared and paid per common share", "$ 0.485", "", "", "", "", ""], ["Stock-based compensation", "$ 248", "", "248", "", "", ""], ["Reclassification of convertible debt conversion obligation", "$ 55", "", "55", "", "", ""], ["Ending common stock, shares, outstanding at Jan. 29, 2017", "585", "585", "", "", "", ""], ["Ending Balances, shareholders' equity at Jan. 29, 2017", "$ 5,762", "$ 1", "4,708", "(5,039)", "(16)", "6,108"], ["Retained earnings adjustment due to adoption of an accounting standard related to retained earnings adjustment due to adoption of an accounting standard related to income tax consequences of an intra-entity transfer of an asset", "(27)", "", "", "", "", "(27)"], ["Other comprehensive income (loss)", "(2)", "", "", "", "(2)", ""], ["Net income", "3,047", "", "", "", "", "3,047"], ["Issuance of common stock in exchange for warrants, shares", "", "13", "", "", "", ""], ["Issuance of common stock from stock plans, shares", "", "18", "", "", "", ""], ["Issuance of common stock from stock plans, value", "$ 138", "", "138", "", "", ""], ["Convertible debt conversion, shares", "33", "33", "", "", "", ""], ["Convertible debt conversion, value", "$ (7)", "", "(7)", "", "", ""], ["Tax withholding related to vesting of restricted stock units, shares", "", "(4)", "", "", "", ""], ["Tax withholding related to vesting of restricted stock units, value", "(612)", "", "", "(612)", "", ""], ["Share repurchase, shares", "", "(6)", "", "", "", ""], ["Share repurchase, value", "(909)", "", "", "(909)", "", ""], ["Exercise of convertible note hedges, shares", "", "33", "", "", "", ""], ["Exercise of convertible note hedges - APIC, value", "", "", "90", "", "", ""], ["Exercise of convertible note hedges - treasury stock, value", "", "", "", "(90)", "", ""], ["Cash dividends declared and paid", "$ (341)", "", "", "", "", "(341)"], ["Cash dividends declared and paid per common share", "$ 0.570", "", "", "", "", ""], ["Stock-based compensation", "$ 391", "", "391", "", "", ""], ["Reclassification of convertible debt conversion obligation", "$ 31", "", "31", "", "", ""], ["Ending common stock, shares, outstanding at Jan. 28, 2018", "606", "606", "", "", "", ""], ["Ending Balances, shareholders' equity at Jan. 28, 2018", "$ 7,471", "$ 1", "$ 5,351", "$ (6,650)", "$ (18)", "$ 8,787"]]}, {"headers": [["CONSOLIDATED STATEMENTS OF CASH FLOWS - USD ($) $ in Millions", "12 Months Ended"], ["Jan. 28, 2018", "Jan. 29, 2017", "Jan. 31, 2016"]], "sections": ["Cash flows from operating activities:", "Adjustments to reconcile net income to net cash provided by operating activities:", "Changes in operating assets and liabilities:", "Cash flows from investing activities:", "Cash flows from financing activities:", "Supplemental disclosures of cash flow information:", "Non-cash investing and financing activity:"], "data": [["Net income", "$ 3,047", "$ 1,666", "$ 614"], ["Stock-based compensation expense", "391", "247", "204"], ["Depreciation and amortization", "199", "187", "197"], ["Loss on early debt conversions", "19", "21", "0"], ["Amortization of debt discount", "3", "25", "29"], ["Deferred income taxes", "(359)", "197", "134"], ["Net gain on sale and disposal of long-lived assets and investments", "(1)", "(3)", "(6)"], ["Restructuring and other charges", "0", "0", "45"], ["Tax benefit from stock-based compensation", "0", "0", "(10)"], ["Other", "18", "11", "19"], ["Accounts receivable", "(440)", "(321)", "(32)"], ["Inventories", "0", "(375)", "66"], ["Prepaid expenses and other assets", "21", "(18)", "(16)"], ["Accounts payable", "90", "184", "(11)"], ["Accrued and other current liabilities", "33", "(135)", "39"], ["Other long-term liabilities", "481", "(14)", "(97)"], ["Net cash provided by operating activities", "3,502", "1,672", "1,175"], ["Proceeds from sales of marketable securities", "863", "1,546", "2,102"], ["Proceeds from maturities of marketable securities", "1,078", "969", "1,036"], ["Proceeds from sale of long-lived assets and investments", "2", "7", "7"], ["Purchases of marketable securities", "(36)", "(3,134)", "(3,477)"], ["Purchases of property and equipment and intangible assets", "(593)", "(176)", "(86)"], ["Reimbursement of building development costs from banks", "0", "0", "24"], ["Investment in non-affiliates", "(36)", "(5)", "(6)"], ["Net cash provided by (used in) investing activities", "1,278", "(793)", "(400)"], ["Proceeds from issuance of debt", "0", "1,988", "0"], ["Payments related to repurchases of common stock", "(909)", "(739)", "(587)"], ["Repayment of Convertible Notes", "(812)", "(673)", "0"], ["Dividends paid", "(341)", "(261)", "(213)"], ["Proceeds related to employee stock plans", "139", "167", "186"], ["Payments related to tax on restricted stock units", "(612)", "(176)", "(66)"], ["Payments for debt issuance costs", "0", "(8)", "0"], ["Tax benefit from stock-based compensation", "0", "0", "10"], ["Other", "(9)", "(7)", "(6)"], ["Net cash provided by (used in) financing activities", "(2,544)", "291", "(676)"], ["Change in cash and cash equivalents", "2,236", "1,170", "99"], ["Cash and cash equivalents at beginning of period", "1,766", "596", "497"], ["Cash and cash equivalents at end of period", "4,002", "1,766", "596"], ["Cash paid for income taxes, net", "22", "14", "14"], ["Cash paid for interest", "55", "13", "17"], ["Assets acquired by assuming related liabilities", "$ 36", "$ 16", "$ 19"]]}]